main.py
pypaye-0.1.2.dist-info/entry_points.txt
pypaye-0.1.2.dist-info/LICENSE.md
pypaye-0.1.2.dist-info/WHEEL
pypaye-0.1.2.dist-info/METADATA
pypaye-0.1.2.dist-info/RECORD
